jptel/__init__.py
jptel/exception.py
jptel/jptel.py
jptel/data/__init__.py
jptel/data/_generate_master_data.py
jptel/data/area_code.py
jptel/data/defined_code.py
jptel-0.1.2.dist-info/DESCRIPTION.rst
jptel-0.1.2.dist-info/METADATA
jptel-0.1.2.dist-info/RECORD
jptel-0.1.2.dist-info/WHEEL
jptel-0.1.2.dist-info/metadata.json
jptel-0.1.2.dist-info/top_level.txt
