Metadata-Version: 2.0
Name: jptel
Version: 0.1.2
Summary: Japanese Telephone Number Utility
Home-page: https://github.com/zenwerk/jptel-py
Author: zenwerk
Author-email: zenwerk@gmail.com
License: MIT
Keywords: japaneses telephone number
Platform: UNKNOWN
Classifier: Programming Language :: Python :: 3.7
Classifier: License :: OSI Approved :: MIT License
